[
  {
    "algorithm": "LIMBO",
    "cluster": 8,
    "class": "org.apache.hadoop.mapreduce.InputFormat",
    "path": "InputFormat.java",
    "file_name": "InputFormat.java",
    "directory": ".",
    "summary": "KEY FUNCTIONALITY: main purpose visible in this chunk\nThe main purpose of this code chunk is to define the abstract class `InputFormat` for Hadoop MapReduce jobs. This class outlines the contract for input specifications, including splitting input files into logical `InputSplit`s and providing a `RecordReader` for processing.\n\nCORE LOGIC: key algorithms or processing patterns visible in this chunk\nThe core logic involves two abstract methods:\n1. `getSplits(JobContext context)`: This method is responsible for logically splitting the input files for the job into `InputSplit`s. Each split is then assigned to an individual `Mapper` for processing. The splitting is based on input size, with the file system block size as an upper bound.\n2. `createRecordReader(InputSplit split, TaskAttemptContext context)`: This method creates a `RecordReader` for a given `InputSplit`. The framework initializes the `RecordReader` using `initialize(InputSplit, TaskAttemptContext)` before the split is used.\n\nINPUTS/OUTPUTS: data flowing in and out\n- INPUTS: `JobContext` object containing job configuration details.\n- OUTPUTS: An array of `InputSplit` objects, each representing a logical chunk of the input data.\n\nDEPENDENCIES: key imported, parent, or collaborator classes visible in this chunk\n- `java.io.IOException`\n- `java.util.List`\n- `org.apache.hadoop.classification.InterfaceAudience`\n- `org.apache.hadoop.classification.InterfaceStability`\n- `org.apache.hadoop.fs.FileSystem`\n- `org.apache.hadoop.mapreduce.lib.input.FileInputFormat`\n- `org.apache.hadoop.mapreduce.JobContext`\n- `org.apache.hadoop.mapreduce.TaskAttemptContext`\n- `org.apache.hadoop.mapreduce.InputSplit`\n- `org.apache.hadoop.mapreduce.RecordReader`",
    "chunked": false,
    "number_of_code_chunks": 1,
    "chunk_summaries": []
  },
  {
    "algorithm": "LIMBO",
    "cluster": 8,
    "class": "org.apache.hadoop.mapreduce.RecordReader",
    "path": "RecordReader.java",
    "file_name": "RecordReader.java",
    "directory": ".",
    "summary": "KEY FUNCTIONALITY: The main purpose of this code chunk is to define an abstract class `RecordReader` for Hadoop MapReduce framework. This class is responsible for breaking down input data into key/value pairs for consumption by the `Mapper`.\n\nCORE LOGIC: The core logic involves defining an abstract class with methods that need to be implemented by concrete record reader classes. These methods include:\n- `initialize(InputSplit split, TaskAttemptContext context)`: Called once at initialization to set up the reader with the given split (range of records) and task context.\n- `nextKeyValue()`: Returns true if a key/value pair is available, false otherwise.\n- `getCurrentKey()`: Returns the current key, or null if no current key exists.\n- `getCurrentValue()`: Returns the current value (the data read).\n- `getProgress()`: Returns the progress of the record reader through its data, a float value between 0.0 and 1.0.\n- `close()`: Closes the record reader, releasing any resources.\n\nINPUTS/OUTPUTS: The `RecordReader` class doesn't directly handle inputs or outputs. Instead, it prepares and provides key-value pairs as output to the `Mapper`. The actual reading from input sources (like files) is handled by concrete implementations of this abstract class.\n\nDEPENDENCIES: The key dependencies visible in this chunk are:\n- `InputSplit`: Represents a logical chunk of the input for a MapReduce job.\n- `TaskAttemptContext`: Provides information about the task attempt, such as configuration and logging.\n- `IOException`: Standard exception for I/O errors.\n- `InterruptedException`: Exception indicating that a thread has been interrupted.\n\nThis class also imports standard Java classes like `Closeable`, and specific Hadoop classes from the `org.apache.hadoop.mapreduce` package, indicating its collaboration within the Hadoop MapReduce framework.",
    "chunked": false,
    "number_of_code_chunks": 1,
    "chunk_summaries": []
  },
  {
    "algorithm": "LIMBO",
    "cluster": 8,
    "class": "org.apache.hadoop.mapreduce.lib.input.CombineFileInputFormat",
    "path": "lib/input/CombineFileInputFormat.java",
    "file_name": "CombineFileInputFormat.java",
    "directory": "lib/input",
    "summary": "KEY FUNCTIONALITY:\nThe main purpose of this code chunk, specifically the `CombineFileInputFormat.java` file, is to define an abstract input format for Hadoop MapReduce that generates `CombineFileSplit` objects. This class ensures that splits do not contain files from different pools and can combine blocks from different files within a single split, thereby optimizing data processing.\n\nCORE LOGIC:\nThe core logic revolves around creating and managing pools of input paths, filtering files based on these pools, and generating `InputSplit` objects based on specified maximum, minimum split sizes, and rack-based constraints. The `getSplits` method iterates through the input files, categorizes them into pools, and then generates splits based on the specified constraints. The `createSplits` method processes nodes and creates node-local splits, while also handling overflow blocks for rack-based splits.\n\nINPUTS/OUTPUTS:\nThe inputs to this class are `JobContext`, `Configuration`, and a list of `FileStatus` objects representing input files. The outputs are a list of `InputSplit` objects, which represent the logical partitions of the input data for processing by MapReduce tasks.\n\nDEPENDENCIES:\nThis code chunk depends on several classes and interfaces from the Hadoop MapReduce library, including:\n\n- `InputFormat`\n- `InputSplit`\n- `JobContext`\n- `TaskAttemptContext`\n- `RecordReader`\n- `Configuration`\n- `Path`\n- `FileStatus`\n- `CompressionCodec`\n- `SplittableCompressionCodec`\n- `MultiPathFilter`\n- `OneFileInfo`\n- `OneBlockInfo`\n- `HashMultiset` from Google Guava (third-party dependency)\n\nAdditionally, it uses standard Java classes like `ArrayList`, `List`, `HashMap`, `Set`, `Iterator`, and `Configuration`.\n\nThe second chunk focuses on processing and organizing block information for input splits in Apache Hadoop MapReduce. It specifically deals with creating input splits from a list of blocks, ensuring that the size of each split does not exceed a specified maximum size.\n\nCORE LOGIC:\nThe core logic involves iterating over a list of blocks (`overflowBlocks`), accumulating their sizes (`curSplitSize`), and tracking their rack locations (`racks`). When the accumulated size reaches or exceeds a maximum size (`maxSize`), a new input",
    "chunked": true,
    "number_of_code_chunks": 2,
    "chunk_summaries": [
      "KEY FUNCTIONALITY: The main purpose of this code chunk is to define the `CombineFileInputFormat` class, an abstract input format for Hadoop MapReduce that generates `CombineFileSplit` objects. This class ensures that splits do not contain files from different pools and can combine blocks from different files within a single split.\n\nCORE LOGIC: The core logic involves creating and managing pools of input paths, filtering files based on these pools, and generating `InputSplit` objects based on specified maximum, minimum split sizes, and rack-based constraints. The `getSplits` method iterates through the input files, categorizes them into pools, and then generates splits based on the specified constraints. The `createSplits` method processes nodes and creates node-local splits, while also handling overflow blocks for rack-based splits.\n\nINPUTS/OUTPUTS: The inputs to this class are JobContext, Configuration, and a list of FileStatus objects representing input files. The outputs are a list of InputSplit objects, which represent the logical partitions of the input data for processing by MapReduce tasks.\n\nDEPENDENCIES: This code chunk depends on several classes and interfaces from the Hadoop MapReduce library, including:\n\n- `InputFormat`\n- `InputSplit`\n- `JobContext`\n- `TaskAttemptContext`\n- `RecordReader`\n- `Configuration`\n- `Path`\n- `FileStatus`\n- `CompressionCodec`\n- `SplittableCompressionCodec`\n- `MultiPathFilter`\n- `OneFileInfo`\n- `OneBlockInfo`\n- `HashMultiset` from Google Guava (third-party dependency)\n\nAdditionally, it uses standard Java classes like `ArrayList`, `List`, `HashMap`, `Set`, `Iterator`, and `Configuration`.",
      "KEY FUNCTIONALITY:\nThe main purpose of this code chunk is to process and organize block information for input splits in Apache Hadoop MapReduce. It specifically deals with creating input splits from a list of blocks, ensuring that the size of each split does not exceed a specified maximum size.\n\nCORE LOGIC:\nThe core logic involves iterating over a list of blocks (`overflowBlocks`), accumulating their sizes (`curSplitSize`), and tracking their rack locations (`racks`). When the accumulated size reaches or exceeds a maximum size (`maxSize`), a new input split (`CombineFileSplit`) is created using the gathered block information (file paths, offsets, lengths, and rack locations). This process repeats until all blocks are processed, with any remaining blocks also being turned into input splits if they exist.\n\nINPUTS/OUTPUTS:\n- INPUTS: `overflowBlocks` (a list of `OneBlockInfo` objects containing block details), `maxSize` (maximum size for each split), `validBlocks` (a list of currently valid blocks), `racks` (a set of rack locations), `splits` (an arraylist to store created input splits).\n- OUTPUTS: `splits` (an arraylist containing `CombineFileSplit` objects, each representing a split with file paths, offsets, lengths, and rack locations).\n\nDEPENDENCIES:\n- `OneBlockInfo`: Represents information about a single block from the file system.\n- `CombineFileSplit`: Represents a split combining multiple blocks.\n- `PathFilter`: Interface for filtering paths.\n- `MultiPathFilter`: A class implementing `PathFilter` to accept paths based on multiple filters.\n- `FileSystem` and `FileStatus`: For interacting with the Hadoop FileSystem.\n- `NodeBase` and `NetworkTopology`: For handling network topology information.\n- `Path`: Represents a file system path.\n- `BlockLocation`: Contains information about where a block is located in the cluster.\n- `Configuration`: Hadoop configuration object.\n- `TaskAttemptContext`: Context for a task attempt, providing access to Hadoop services.\n- `RecordReader`: Reads map output values.\n- `IOException`: Exception thrown when I/O errors occur."
    ]
  },
  {
    "algorithm": "LIMBO",
    "cluster": 8,
    "class": "org.apache.hadoop.mapreduce.lib.input.CombineFileRecordReader",
    "path": "lib/input/CombineFileRecordReader.java",
    "file_name": "CombineFileRecordReader.java",
    "directory": "lib/input",
    "summary": "KEY FUNCTIONALITY:\nThe main purpose of this code chunk is to define a generic RecordReader class, `CombineFileRecordReader`, that can handle different RecordReaders for each chunk in a `CombineFileSplit`. This allows for the use of different RecordReaders for processing data chunks from different files.\n\nCORE LOGIC:\nThe core logic involves initializing a RecordReader for each chunk in a `CombineFileSplit`. The `initNextRecordReader()` method is responsible for creating and initializing the RecordReader for the next chunk. It closes the current RecordReader if it exists, sets up configuration parameters for the new RecordReader, and then instantiates and initializes the new RecordReader.\n\nINPUTS/OUTPUTS:\nThe class takes in a `CombineFileSplit` object, a `TaskAttemptContext` object, and a class object representing the RecordReader to be used for each chunk. It outputs key-value pairs (K, V) and manages the progress of data processing.\n\nDEPENDENCIES:\nThe key imported or collaborator classes visible in this chunk are:\n- `org.apache.hadoop.mapreduce.InputSplit` (implicitly through `CombineFileSplit`)\n- `org.apache.hadoop.mapreduce.TaskAttemptContext`\n- `org.apache.hadoop.conf.Configuration`\n- `org.apache.hadoop.mapreduce.lib.input.CombineFileSplit`\n- `org.apache.hadoop.classification.InterfaceAudience`\n- `org.apache.hadoop.classification.InterfaceStability`\n- `org.apache.hadoop.mapreduce.RecordReader`",
    "chunked": false,
    "number_of_code_chunks": 1,
    "chunk_summaries": []
  },
  {
    "algorithm": "LIMBO",
    "cluster": 8,
    "class": "org.apache.hadoop.mapreduce.lib.input.CombineFileRecordReaderWrapper",
    "path": "lib/input/CombineFileRecordReaderWrapper.java",
    "file_name": "CombineFileRecordReaderWrapper.java",
    "directory": "lib/input",
    "summary": "KEY FUNCTIONALITY:\nThe main purpose of this class is to serve as a wrapper for a RecordReader that handles a single file split in a CombineFileInputFormat context. It ensures that the delegate RecordReader is initialized with the correct FileSplit based on the configuration parameters.\n\nCORE LOGIC:\nThe core logic involves creating a FileSplit object from the given CombineFileSplit and using it to initialize the delegate RecordReader. The `fileSplitIsValid` method checks if the configuration parameters match the FileSplit attributes to ensure correctness.\n\nINPUTS/OUTPUTS:\n- Inputs: FileSplit, TaskAttemptContext, CombineFileSplit, Configuration\n- Outputs: None explicitly, but it delegates RecordReader methods to its delegate, providing key-value pairs and progress information.\n\nDEPENDENCIES:\n- Imported classes: java.io.IOException\n- Parent/Collaborator classes: org.apache.hadoop.mapreduce.lib.input.FileInputFormat, org.apache.hadoop.mapreduce.RecordReader, org.apache.hadoop.mapreduce.InputSplit, org.apache.hadoop.mapreduce.MRJobConfig, org.apache.hadoop.conf.Configuration, org.apache.hadoop.mapreduce.TaskAttemptContext\n- Interfaces: org.apache.hadoop.mapreduce.RecordReader, org.apache.hadoop.mapreduce.InputSplit\n\nThis class is part of the Apache Hadoop MapReduce library, specifically within the input handling module (`org.apache.hadoop.mapreduce.lib.input`). It's designed to work with `CombineFileInputFormat`, which combines multiple file splits into a single logical split, facilitating efficient processing of data stored across multiple files. The `CombineFileRecordReaderWrapper` ensures that the delegate RecordReader is correctly initialized with the appropriate file split based on the configuration parameters.",
    "chunked": false,
    "number_of_code_chunks": 1,
    "chunk_summaries": []
  },
  {
    "algorithm": "LIMBO",
    "cluster": 8,
    "class": "org.apache.hadoop.mapreduce.lib.input.DelegatingInputFormat",
    "path": "lib/input/DelegatingInputFormat.java",
    "file_name": "DelegatingInputFormat.java",
    "directory": "lib/input",
    "summary": "KEY FUNCTIONALITY:\nThe main purpose of this code chunk is to define the `getSplits` method of the `DelegatingInputFormat` class, which is responsible for delegating the behavior of paths to multiple other InputFormats.\n\nCORE LOGIC:\nThe core logic involves creating a map of InputFormats to Paths (`formatPaths`), then for each set of paths that share a common InputFormat, building a map of Mappers to the paths they're used for (`mapperPaths`). It then iterates over these maps, creating InputSplits for each path, tagging them with the InputFormat and Mapper types, and adding them to the list of splits to be returned.\n\nINPUTS/OUTPUTS:\n- Inputs: JobContext (`job`), Configuration (`conf`), InputFormatMap (`formatMap`), MapperTypeMap (`mapperMap`)\n- Outputs: A list of `InputSplit` objects (`splits`), which are created by delegating to other InputFormats based on the paths and their corresponding Mappers.\n\nDEPENDENCIES:\n- Imported classes: `java.io.IOException`, `java.util.ArrayList`, `java.util.HashMap`, `java.util.LinkedList`, `java.util.List`, `java.util.Map`, `java.util.Map.Entry`\n- Parent/Collaborator classes: `org.apache.hadoop.mapreduce.lib.input.DelegatingInputFormat`, `org.apache.hadoop.classification.InterfaceAudience`, `org.apache.hadoop.classification.InterfaceStability`, `org.apache.hadoop.conf.Configuration`, `org.apache.hadoop.fs.Path`, `org.apache.hadoop.mapreduce.InputFormat`, `org.apache.hadoop.mapreduce.InputSplit`, `org.apache.hadoop.mapreduce.Job`, `org.apache.hadoop.mapreduce.JobContext`, `org.apache.hadoop.mapreduce.Mapper`, `org.apache.hadoop.mapreduce.RecordReader`, `org.apache.hadoop.mapreduce.TaskAttemptContext`, `org.apache.hadoop.util.ReflectionUtils`\n- Methods/functions used: `MultipleInputs.getInputFormatMap(Job)`, `MultipleInputs.getMapperTypeMap(Job)`, `ReflectionUtils.newInstance(Class, Configuration)`, `FileInputFormat.setInputPaths(Job, Path[])`",
    "chunked": false,
    "number_of_code_chunks": 1,
    "chunk_summaries": []
  },
  {
    "algorithm": "LIMBO",
    "cluster": 8,
    "class": "org.apache.hadoop.mapreduce.lib.input.DelegatingRecordReader",
    "path": "lib/input/DelegatingRecordReader.java",
    "file_name": "DelegatingRecordReader.java",
    "directory": "lib/input",
    "summary": "KEY FUNCTIONALITY:\nThe main purpose of this code chunk is to define a delegating RecordReader class in Apache Hadoop MapReduce that delegates functionality to an underlying RecordReader in a TaggedInputSplit.\n\nCORE LOGIC:\nThe core logic involves creating an instance of the DelegatingRecordReader, which takes an InputSplit and TaskAttemptContext as parameters in its constructor. It then uses reflection to instantiate an InputFormat from the class specified in the TaggedInputSplit. With this InputFormat instance, it creates an underlying RecordReader using the createRecordReader method, which is then stored in the 'originalRR' variable. The DelegatingRecordReader class extends RecordReader<K, V> and overrides several methods (close, getCurrentKey, getCurrentValue, getProgress, initialize, nextKeyValue) to delegate their functionality to the 'originalRR'.\n\nINPUTS/OUTPUTS:\nInputs:\n- InputSplit split: An object representing a segment of the input data.\n- TaskAttemptContext context: Provides information about the task being performed.\n\nOutputs: None explicitly shown in this chunk. The delegated RecordReader processes the input data and provides key-value pairs as outputs, which are then returned by the delegated methods.\n\nDEPENDENCIES:\n- org.apache.hadoop.mapreduce.lib.input.TaggedInputSplit: The input split that contains the actual input format class.\n- org.apache.hadoop.mapreduce.InputFormat<K, V>: The format of the input data.\n- org.apache.hadoop.mapreduce.RecordReader<K, V>: The class to be delegated.\n- org.apache.hadoop.util.ReflectionUtils: Used for creating instances via reflection.\n- java.io.IOException: Thrown for input/output exceptions.\n- java.util.concurrent.InterruptedException: Thrown if a thread is waiting for a notification that is never received.\n\nKey imported classes:\n```java\nimport java.io.IOException;\n\nimport org.apache.hadoop.classification.InterfaceAudience;\nimport org.apache.hadoop.classification.InterfaceStability;\nimport org.apache.hadoop.mapreduce.InputFormat;\nimport org.apache.hadoop.mapreduce.InputSplit;\nimport org.apache.hadoop.mapreduce.RecordReader;\nimport org.apache.hadoop.mapreduce.TaskAttemptContext;\nimport org.apache.hadoop",
    "chunked": false,
    "number_of_code_chunks": 1,
    "chunk_summaries": []
  },
  {
    "algorithm": "LIMBO",
    "cluster": 8,
    "class": "org.apache.hadoop.mapreduce.lib.input.FixedLengthInputFormat",
    "path": "lib/input/FixedLengthInputFormat.java",
    "file_name": "FixedLengthInputFormat.java",
    "directory": "lib/input",
    "summary": "KEY FUNCTIONALITY:\nThe main purpose of this code chunk is to define the `FixedLengthInputFormat` class, which is an input format for Hadoop MapReduce used to read fixed-length records from input files. These records can be binary data, not necessarily text. The class provides methods to set and get the record length, and it creates a `FixedLengthRecordReader` for processing the input data.\n\nCORE LOGIC:\nThe core logic of this class revolves around managing the fixed-length records in input files. It includes methods to set and get the record length, and a method to create a `FixedLengthRecordReader` that reads the input data based on the specified record length. The `isSplitable` method checks if the input file is splittable based on its compression.\n\nINPUTS/OUTPUTS:\n- Inputs: Configuration (for setting record length), JobContext, Path (file to be read), TaskAttemptContext\n- Outputs: RecordReader (FixedLengthRecordReader) that reads fixed-length records from the input file\n\nDEPENDENCIES:\n- `org.apache.hadoop.classification`: For annotations\n- `org.apache.hadoop.conf`: For Configuration class\n- `org.apache.hadoop.fs`: For Path class\n- `org.apache.hadoop.io`: For LongWritable, BytesWritable classes\n- `org.apache.hadoop.io.compress`: For CompressionCodec and CompressionCodecFactory classes\n- `org.apache.hadoop.mapreduce`: For InputSplit, JobContext, RecordReader, TaskAttemptContext classes\n- `org.apache.hadoop.mapreduce.lib.input`: Parent class FileInputFormat",
    "chunked": false,
    "number_of_code_chunks": 1,
    "chunk_summaries": []
  },
  {
    "algorithm": "LIMBO",
    "cluster": 8,
    "class": "org.apache.hadoop.mapreduce.lib.input.FixedLengthRecordReader",
    "path": "lib/input/FixedLengthRecordReader.java",
    "file_name": "FixedLengthRecordReader.java",
    "directory": "lib/input",
    "summary": "KEY FUNCTIONALITY:\nThe main purpose of this class is to implement a RecordReader for reading fixed-length records from a split in Apache Hadoop MapReduce. It extends the RecordReader class and is designed to read key-value pairs, where the key is a LongWritable and the value is a BytesWritable.\n\nCORE LOGIC:\nThe core logic involves initializing the reader with a given record length, setting up file input streams, handling compression if necessary, and implementing the nextKeyValue() method to read fixed-length records from the input split. The class also provides methods to get the current key and value, progress tracking, and proper resource cleanup in the close() method.\n\nINPUTS/OUTPUTS:\n- Inputs: The class takes an integer 'recordLength' as input during initialization, representing the length of each fixed-length record. It also takes an InputSplit, TaskAttemptContext, and Configuration object during the initialize() method call.\n- Outputs: The class outputs key-value pairs, where the key is of type LongWritable and the value is of type BytesWritable. The key represents the byte offset of the record, and the value contains the actual bytes of the record.\n\nDEPENDENCIES:\n- Imported classes: The class imports various Hadoop-related classes, including FSDataInputStream, FutureDataInputStreamBuilder, Path, Seekable, BytesWritable, LongWritable, CompressionCodec, CompressionCodecFactory, CompressionInputStream, Decompressor, InputSplit, TaskAttemptContext, Configuration, MRJobConfig, RecordReader, and Logger.\n- Collaborator classes: The class extends RecordReader<LongWritable, BytesWritable>, and it interacts with Hadoop's FSDataInputStream, FutureIO, CompressionCodecFactory, and other Hadoop-related classes to handle file input, compression, and progress tracking.",
    "chunked": false,
    "number_of_code_chunks": 1,
    "chunk_summaries": []
  },
  {
    "algorithm": "LIMBO",
    "cluster": 8,
    "class": "org.apache.hadoop.mapreduce.lib.input.KeyValueLineRecordReader",
    "path": "lib/input/KeyValueLineRecordReader.java",
    "file_name": "KeyValueLineRecordReader.java",
    "directory": "lib/input",
    "summary": "KEY FUNCTIONALITY:\nThe main purpose of this class is to implement a RecordReader for key-value pairs in Hadoop MapReduce, where each line in the input is treated as a key/value pair separated by a specified separator character.\n\nCORE LOGIC:\nThe core logic involves initializing a LineRecordReader, setting the separator character from the configuration, and implementing methods to read key-value pairs from the input. The `nextKeyValue()` method is central, finding the separator in the line and setting the key and value Text objects accordingly.\n\nINPUTS/OUTPUTS:\n- Inputs: InputSplit and TaskAttemptContext objects for initialization.\n- Configuration object to get the separator character.\n- Outputs: Text objects for key and value, representing the parsed key-value pair from each line.\n\nDEPENDENCIES:\n- org.apache.hadoop.classification: For interface annotations.\n- org.apache.hadoop.conf: For Configuration class.\n- org.apache.hadoop.io: For Text class.\n- org.apache.hadoop.mapreduce: For InputSplit, RecordReader, and TaskAttemptContext classes.\n- org.apache.hadoop.mapreduce.lib.input: Parent package for LineRecordReader.",
    "chunked": false,
    "number_of_code_chunks": 1,
    "chunk_summaries": []
  },
  {
    "algorithm": "LIMBO",
    "cluster": 8,
    "class": "org.apache.hadoop.mapreduce.lib.input.KeyValueTextInputFormat",
    "path": "lib/input/KeyValueTextInputFormat.java",
    "file_name": "KeyValueTextInputFormat.java",
    "directory": "lib/input",
    "summary": "KEY FUNCTIONALITY:\nThe main purpose of this code chunk is to define the `KeyValueTextInputFormat` class, which extends `FileInputFormat<Text, Text>`. This class is designed to handle plain text files, breaking them into lines and dividing each line into key and value parts using a specified separator byte.\n\nCORE LOGIC:\nThe core logic involves overriding the `isSplitable` method to determine if a file can be split. It checks if the file is compressed and if the compression codec is splittable. The `createRecordReader` method is overridden to create a new instance of `KeyValueLineRecordReader`, which reads the key-value pairs from the text file.\n\nINPUTS/OUTPUTS:\nInputs: The class takes a `JobContext` and `Path` object as inputs in the `isSplitable` method. In the `createRecordReader` method, it takes an `InputSplit` and `TaskAttemptContext` object.\n\nOutputs: The class does not explicitly return any output. Instead, it sets the status of the `TaskAttemptContext` in the `createRecordReader` method and returns a `RecordReader<Text, Text>` instance.\n\nDEPENDENCIES:\nThe code chunk depends on several classes from the `org.apache.hadoop` package, including `CompressionCodec`, `CompressionCodecFactory`, `SplittableCompressionCodec`, `InputFormat`, `InputSplit`, `JobContext`, `RecordReader`, and `TaskAttemptContext`. It also imports standard Java classes like `IOException` and `Path`. Additionally, it uses `org.apache.hadoop.io.Text` for key-value pairs and `org.apache.hadoop.mapreduce.lib.input.FileInputFormat` as the parent class.",
    "chunked": false,
    "number_of_code_chunks": 1,
    "chunk_summaries": []
  },
  {
    "algorithm": "LIMBO",
    "cluster": 8,
    "class": "org.apache.hadoop.mapreduce.lib.input.LineRecordReader",
    "path": "lib/input/LineRecordReader.java",
    "file_name": "LineRecordReader.java",
    "directory": "lib/input",
    "summary": "KEY FUNCTIONALITY:\nThe main purpose of this class, LineRecordReader, is to read key-value pairs from a file where keys are byte offsets and values are lines of text. It handles both compressed and uncompressed files, and it can skip UTF-8 Byte Order Marks (BOM) if present.\n\nCORE LOGIC:\n- The class extends RecordReader, overriding methods to implement custom reading logic.\n- The `initialize` method sets up the file input stream, handles compression, and initializes the line reader (SplitLineReader, CompressedSplitLineReader, or UncompressedSplitLineReader).\n- The `nextKeyValue` method reads lines from the file, handling cases where lines might span split boundaries and could be longer than the specified maximum line length.\n- The `getProgress` method calculates the progress within the current split.\n- The `close` method ensures proper cleanup of resources, including closing the line reader and returning the decompressor to the pool.\n\nINPUTS/OUTPUTS:\n- INPUTS: FileSplit object, TaskAttemptContext, Configuration (for job settings)\n- OUTPUTS: Key-value pairs of LongWritable (key) and Text (value)\n\nDEPENDENCIES:\n- Imported classes include various Hadoop components:\n  - org.apache.hadoop.fs.* for file system operations\n  - org.apache.hadoop.io.* for basic I/O types\n  - org.apache.hadoop.mapreduce.* for MapReduce framework components\n  - org.apache.hadoop.util.functional.FutureIO for asynchronous I/O\n  - org.slf4j.* for logging\n- Collaborates with classes in the Hadoop ecosystem, such as FSDataInputStream, CompressionCodec, SplitCompressionInputStream, and RecordReader.",
    "chunked": false,
    "number_of_code_chunks": 1,
    "chunk_summaries": []
  },
  {
    "algorithm": "LIMBO",
    "cluster": 8,
    "class": "org.apache.hadoop.mapreduce.lib.input.NLineInputFormat",
    "path": "lib/input/NLineInputFormat.java",
    "file_name": "NLineInputFormat.java",
    "directory": "lib/input",
    "summary": "KEY FUNCTIONALITY: The main purpose of this code chunk is to define the `NLineInputFormat` class, which is a custom input format for Apache Hadoop MapReduce. It splits input files into splits, where each split contains a specified number of lines (`numLinesPerSplit`).\n\nCORE LOGIC: The core logic involves the `getSplits` method, which iterates through the input files and generates `InputSplit` objects for each file. For each file, it calls `getSplitsForFile`, which reads the file line by line using a `LineReader`. When the number of lines in the current split reaches `numLinesPerSplit`, a `FileSplit` object is created and added to the list of splits. The `createFileSplit` method adjusts the upper boundary of each split by subtracting one character to ensure that each mapper receives the correct number of lines.\n\nINPUTS/OUTPUTS: The input to this class is a `JobContext` object, which contains information about the job, including configuration settings. The output is a list of `InputSplit` objects, each representing a portion of the input files to be processed by individual map tasks.\n\nDEPENDENCIES: This code chunk depends on several classes from the Apache Hadoop MapReduce library, including:\n\n- `org.apache.hadoop.mapreduce.InputSplit`\n- `org.apache.hadoop.mapreduce.JobContext`\n- `org.apache.hadoop.mapreduce.RecordReader`\n- `org.apache.hadoop.mapreduce.TaskAttemptContext`\n- `org.apache.hadoop.fs.FileStatus`\n- `org.apache.hadoop.fs.Path`\n- `org.apache.hadoop.io.LongWritable`\n- `org.apache.hadoop.io.Text`\n- `org.apache.hadoop.conf.Configuration`\n- `org.apache.hadoop.fs.FSDataInputStream`\n- `org.apache.hadoop.fs.FutureDataInputStreamBuilder`\n- `org.apache.hadoop.util.LineReader`\n- `org.apache.hadoop.util.FutureIO`\n\nAdditionally, it uses the `org.apache.hadoop.mapreduce.lib.input.FileInputFormat` class as a superclass.",
    "chunked": false,
    "number_of_code_chunks": 1,
    "chunk_summaries": []
  },
  {
    "algorithm": "LIMBO",
    "cluster": 8,
    "class": "org.apache.hadoop.mapreduce.lib.input.SequenceFileAsTextRecordReader",
    "path": "lib/input/SequenceFileAsTextRecordReader.java",
    "file_name": "SequenceFileAsTextRecordReader.java",
    "directory": "lib/input",
    "summary": "KEY FUNCTIONALITY:\nThe main purpose of this class is to extend the RecordReader interface for Sequence Files, converting the input keys and values to their String forms by calling the toString() method.\n\nCORE LOGIC:\nThe core logic involves initializing a SequenceFileRecordReader, reading key-value pairs, converting them to Text objects, and implementing methods to get the current key, current value, progress, and closing the reader.\n\nINPUTS/OUTPUTS:\n- Input: InputSplit and TaskAttemptContext objects are used to initialize the reader.\n- Output: Key-value pairs are read from the SequenceFile and converted to Text objects, which are then returned by getCurrentKey() and getCurrentValue() methods.\n\nDEPENDENCIES:\n- org.apache.hadoop.mapreduce.lib.input.SequenceFileRecordReader\n- org.apache.hadoop.io.Text\n- org.apache.hadoop.io.Writable\n- org.apache.hadoop.io.WritableComparable\n- org.apache.hadoop.mapreduce.InputSplit\n- org.apache.hadoop.mapreduce.RecordReader\n- org.apache.hadoop.mapreduce.TaskAttemptContext\n- java.io.IOException\n- java.util.concurrent.locks.StuckThreadException (implied by use of InterruptedException)",
    "chunked": false,
    "number_of_code_chunks": 1,
    "chunk_summaries": []
  },
  {
    "algorithm": "LIMBO",
    "cluster": 8,
    "class": "org.apache.hadoop.mapreduce.lib.input.SequenceFileInputFormat",
    "path": "lib/input/SequenceFileInputFormat.java",
    "file_name": "SequenceFileInputFormat.java",
    "directory": "lib/input",
    "summary": "KEY FUNCTIONALITY:\nThe main purpose of this code chunk is to define the `SequenceFileInputFormat` class, which extends `FileInputFormat` and serves as an input format for handling SequenceFiles in Apache Hadoop MapReduce.\n\nCORE LOGIC:\nThe core logic involves overriding methods from the parent class `FileInputFormat` to customize the behavior for reading SequenceFiles. Specifically, it includes:\n\n1. `createRecordReader`: This method returns a new instance of `SequenceFileRecordReader`, which is responsible for reading records from SequenceFiles.\n2. `getFormatMinSplitSize`: This method returns the minimum size of a split when dealing with SequenceFiles, which is defined as `SequenceFile.SYNC_INTERVAL`.\n3. `listStatus`: This method overrides the parent class's implementation to handle MapFiles within SequenceFiles. If a directory (which could contain a MapFile) is encountered, it replaces the directory status with the status of its data file (`MapFile.DATA_FILE_NAME`).\n\nINPUTS/OUTPUTS:\nThe data flow in this context is internal to the Hadoop MapReduce framework. It doesn't directly handle input or output files but prepares the framework to read from SequenceFiles.\n\nDEPENDENCIES:\nKey dependencies visible in this chunk include:\n\n1. `org.apache.hadoop.mapreduce.InputFormat`: The abstract class that `SequenceFileInputFormat` extends.\n2. `org.apache.hadoop.mapreduce.InputSplit`: Represents a logical partition of the input to a mapper.\n3. `org.apache.hadoop.mapreduce.RecordReader`: Responsible for reading individual records from an `InputSplit`.\n4. `org.apache.hadoop.mapreduce.JobContext` and `org.apache.hadoop.mapreduce.TaskAttemptContext`: Context objects providing information about the job and task attempt.\n5. `org.apache.hadoop.fs.FileSystem`, `org.apache.hadoop.fs.FileStatus`, `org.apache.hadoop.io.SequenceFile`, `org.apache.hadoop.io.MapFile`: Classes from the Hadoop I/O and FileSystem libraries used for interacting with SequenceFiles and MapFiles.",
    "chunked": false,
    "number_of_code_chunks": 1,
    "chunk_summaries": []
  },
  {
    "algorithm": "LIMBO",
    "cluster": 8,
    "class": "org.apache.hadoop.mapreduce.lib.input.SequenceFileRecordReader",
    "path": "lib/input/SequenceFileRecordReader.java",
    "file_name": "SequenceFileRecordReader.java",
    "directory": "lib/input",
    "summary": "KEY FUNCTIONALITY:\nThe main purpose of this code chunk is to define the `SequenceFileRecordReader` class, which is a specialized `RecordReader` for reading data from Apache Hadoop Sequence Files.\n\nCORE LOGIC:\nThe core logic involves initializing the reader with a file split in the `initialize` method, advancing the reader position in the Sequence File using `in.sync` and `in.getPosition`, and reading key-value pairs in the `nextKeyValue` method. The `getProgress` method calculates the progress within the input split as a float between 0.0 and 1.0.\n\nINPUTS/OUTPUTS:\n- Inputs: `InputSplit` object and `TaskAttemptContext`\n- Outputs: Key-value pairs of type `K` and `V`, progress as a float\n\nDEPENDENCIES:\n- Imported classes: `java.io.IOException`, `java.util.concurrent.InterruptedException`\n- Collaborator classes: `org.apache.hadoop.classification.InterfaceAudience`, `org.apache.hadoop.classification.InterfaceStability`, `org.apache.hadoop.conf.Configuration`, `org.apache.hadoop.fs.FileSystem`, `org.apache.hadoop.fs.Path`, `org.apache.hadoop.io.Writable`, `org.apache.hadoop.mapreduce.InputSplit`, `org.apache.hadoop.mapreduce.RecordReader`, `org.apache.hadoop.mapreduce.TaskAttemptContext`, `org.apache.hadoop.mapreduce.lib.input.SequenceFile`, `org.apache.hadoop.mapreduce.lib.input.FileSplit`",
    "chunked": false,
    "number_of_code_chunks": 1,
    "chunk_summaries": []
  },
  {
    "algorithm": "LIMBO",
    "cluster": 8,
    "class": "org.apache.hadoop.mapreduce.lib.input.TextInputFormat",
    "path": "lib/input/TextInputFormat.java",
    "file_name": "TextInputFormat.java",
    "directory": "lib/input",
    "summary": "KEY FUNCTIONALITY:\nThe main purpose of this code chunk is to define the `TextInputFormat` class, which extends `FileInputFormat` for processing plain text files in Apache Hadoop MapReduce. It provides methods to create a `RecordReader` for reading lines from the text files and to determine if a file is splittable based on its compression codec.\n\nCORE LOGIC:\n1. The `TextInputFormat` class extends `FileInputFormat<LongWritable, Text>`, indicating that it processes text files, with LongWritable as the key and Text as the value.\n2. The `createRecordReader` method creates a `LineRecordReader` instance, which reads lines from the input files. It takes a `TaskAttemptContext` as an argument to get the record delimiter, which is used to identify the end of a line.\n3. The `isSplitable` method checks if a file can be split into smaller chunks for parallel processing. It determines this by checking the compression codec of the file. If the file is not compressed or if it uses a `SplittableCompressionCodec`, it can be split.\n\nINPUTS/OUTPUTS:\n- INPUTS: The class takes `InputSplit` and `TaskAttemptContext` as inputs for the `createRecordReader` method. It also uses `JobContext` in the `isSplitable` method to get configuration settings and file information.\n- OUTPUTS: The class does not explicitly produce any output. Instead, it prepares the input data for processing by creating a `RecordReader` instance that reads lines from text files and determines if files can be split for parallel processing.\n\nDEPENDENCIES:\n- Imported classes: `org.apache.hadoop.classification.InterfaceAudience`, `org.apache.hadoop.classification.InterfaceStability`, `org.apache.hadoop.fs.Path`, `org.apache.hadoop.io.LongWritable`, `org.apache.hadoop.io.Text`, `org.apache.hadoop.io.compress.CompressionCodec`, `org.apache.hadoop.io.compress.CompressionCodecFactory`, `org.apache.hadoop.io.compress.SplittableCompressionCodec`, `org.apache.hadoop.mapreduce.InputFormat`, `org.apache.hadoop.mapreduce.InputSplit`, `org.apache.hadoop.mapreduce.JobContext`, `org.apache.hadoop.mapreduce.RecordReader`, `org.",
    "chunked": false,
    "number_of_code_chunks": 1,
    "chunk_summaries": []
  },
  {
    "algorithm": "LIMBO",
    "cluster": 8,
    "class": "org.apache.hadoop.mapreduce.lib.join.ComposableInputFormat",
    "path": "lib/join/ComposableInputFormat.java",
    "file_name": "ComposableInputFormat.java",
    "directory": "lib/join",
    "summary": "KEY FUNCTIONALITY:\nThis code snippet defines an abstract class `ComposableInputFormat` in the Apache Hadoop MapReduce library. It extends the `InputFormat` class and is used to create a custom input format for MapReduce jobs. The main purpose of this class is to require implementors to provide a `ComposableRecordReader` instead of a standard `RecordReader`.\n\nCORE LOGIC:\nThe core logic of this class lies in the abstract method `createRecordReader`. This method is meant to be implemented by subclasses, which should return a `ComposableRecordReader` instance. This reader is capable of reading data in a composable manner, meaning it can read data from multiple sources and combine them for processing in a MapReduce job.\n\nINPUTS/OUTPUTS:\nThe class `ComposableInputFormat` does not directly handle any inputs or outputs. Instead, it sets the stage for its subclasses to define how input data should be read. The inputs are expected to be in the form of `InputSplit` objects, which represent a segment of the input dataset, and a `TaskAttemptContext` object, which contains information about the task being performed. The output of this method is a `ComposableRecordReader` instance, which will be used by the framework to read the actual data for processing.\n\nDEPENDENCIES:\nThis class depends on several classes from the Hadoop MapReduce library:\n- `WritableComparable` and `Writable` from `org.apache.hadoop.io` for generic writable types.\n- `InputFormat` from `org.apache.hadoop.mapreduce` for extending the base input format functionality.\n- `InputSplit` from `org.apache.hadoop.mapreduce` to represent a logical partition of the input.\n- `TaskAttemptContext` from `org.apache.hadoop.mapreduce` to provide context information for the task.",
    "chunked": false,
    "number_of_code_chunks": 1,
    "chunk_summaries": []
  }
]